setup.py
alphasign/__init__.py
alphasign/charsets.py
alphasign/colors.py
alphasign/constants.py
alphasign/counters.py
alphasign/date.py
alphasign/extchars.py
alphasign/modes.py
alphasign/packet.py
alphasign/positions.py
alphasign/speeds.py
alphasign/string.py
alphasign/text.py
alphasign/time.py
alphasign.egg-info/PKG-INFO
alphasign.egg-info/SOURCES.txt
alphasign.egg-info/dependency_links.txt
alphasign.egg-info/requires.txt
alphasign.egg-info/top_level.txt
alphasign/interfaces/__init__.py
alphasign/interfaces/base.py
alphasign/interfaces/local.py
