Metadata-Version: 1.0
Name: alphasign
Version: 0.9
Summary: Implementation of the Alpha Sign Communications Protocol
Home-page: http://quadpoint.org/projects/alphasign
Author: Matt Sparks
Author-email: ms@quadpoint.org
License: BSD
Platform: UNKNOWN
